{
    "data": {
        "returnCode": "0",
        "returnValue": {
            "actor": [
                {
                "artisteName": "安东尼·罗素",
                "artisteNameEn": "Anthony Russo",
                "avatar": "i4/TB1DWJYJpXXXXabXFXXXXXXXXXX_.jpg",
                "bornDay": "1970-01-01",
                "id": "903229",
                "roleName": "导演"
            }, {
                "artisteName": "乔·罗素",
                "artisteNameEn": "Joe Russo",
                "avatar": "i4/TB1RBqdJpXXXXXqXXXXXXXXXXXX_.jpg",
                "bornDay": "1971",
                "id": "903230",
                "roleName": "导演"
            }, {
                "artisteName": "小罗伯特·唐尼",
                "artisteNameEn": "Robert Downey Jr.",
                "avatar": "i2/TB1EgVdLFXXXXX7XFXXXXXXXXXX_.jpg",
                "bornDay": "1965-04-04",
                "id": "912602",
                "profession": "演员",
                "roleName": "托尼·斯塔克 / 钢铁侠 "
            }, {
                "artisteName": "克里斯·海姆斯沃斯",
                "artisteNameEn": "Chris Hemsworth",
                "avatar": "i2/TB1I84kLFXXXXahXpXXXXXXXXXX_.jpg",
                "bornDay": "1983-08-11",
                "id": "1425372",
                "profession": "演员",
                "roleName": "索尔 / 雷神 "
            }, {
                "artisteName": "乔什·布洛林",
                "artisteNameEn": "Josh Brolin",
                "avatar": "i1/TB1KB7mrbGYBuNjy0FoXXciBFXa_.jpg",
                "bornDay": "1968-02-12",
                "id": "914053",
                "profession": "演员",
                "roleName": "灭霸 Thanos"
            }, {
                "artisteName": "本尼迪克特·康伯巴奇",
                "artisteNameEn": "Benedict Cumberbatch",
                "avatar": "i3/TB1WWdYLXXXXXbYaXXXXXXXXXXX_.jpg",
                "bornDay": "1976-07-19",
                "id": "938777",
                "profession": "演员",
                "roleName": "史蒂芬·斯特里奇 / 奇异博士"
            }, {
                "artisteName": "克里斯·埃文斯",
                "artisteNameEn": "Chris Evans",
                "avatar": "i4/TB17.A_LpXXXXcxXFXXXXXXXXXX_.jpg",
                "bornDay": "1981-06-13",
                "id": "911885",
                "profession": "演员",
                "roleName": "史蒂夫·罗杰斯 / 美国队长"
            }, {
                "artisteName": "马克·鲁法洛",
                "artisteNameEn": "Mark Ruffalo",
                "avatar": "i4/TB18ZicJpXXXXc8XXXXXXXXXXXX_.jpg",
                "bornDay": "1967-11-22",
                "id": "913614",
                "profession": "演员",
                "roleName": "布鲁斯·班纳 / 绿巨人"
            }, {
                "artisteName": "斯嘉丽·约翰逊",
                "artisteNameEn": "Scarlett Johansson",
                "avatar": "i3/TB1AdDDMXXXXXX6XpXXXXXXXXXX_.jpg",
                "bornDay": "1984-11-22",
                "id": "911751",
                "profession": "演员",
                "roleName": "娜塔莎·罗曼诺夫 / 黑寡妇"
            }, {
                "artisteName": "汤姆·赫兰德",
                "artisteNameEn": "Tom Holland",
                "avatar": "i4/TB1BkxSJpXXXXX0XVXXXXXXXXXX_.jpg",
                "bornDay": "1996-06-01",
                "id": "1796400",
                "profession": "演员",
                "roleName": "彼得·帕克 / 蜘蛛侠"
            }, {
                "artisteName": "唐·钱德尔",
                "artisteNameEn": "Don Cheadle",
                "avatar": "i4/TB1XcSgJFXXXXXhXVXXXXXXXXXX_.jpg",
                "bornDay": "1964-11-29",
                "id": "920630",
                "profession": "演员",
                "roleName": "詹姆斯·罗德 / 战争机器"
            }, {
                "artisteName": "查德维克·博斯曼",
                "artisteNameEn": "Chadwick Boseman",
                "avatar": "i1/TB1anOVLVXXXXXJXFXXXXXXXXXX_.jpg",
                "bornDay": "1976-11-29",
                "id": "1413341",
                "profession": "演员",
                "roleName": "提恰拉 / 黑豹"
            }, {
                "artisteName": "克里斯·帕拉特",
                "artisteNameEn": "Chris Pratt",
                "avatar": "i1/TB1Q7dIJpXXXXadaXXXXXXXXXXX_.jpg",
                "bornDay": "1979-06-21",
                "id": "1098276",
                "profession": "演员",
                "roleName": "彼得·奎尔 / 星爵"
            }, {
                "artisteName": "佐伊·索尔达娜",
                "artisteNameEn": "Zoe Saldana",
                "avatar": "i1/TB1d_PfKVXXXXc5XFXXXXXXXXXX_.jpg",
                "bornDay": "1978-06-19",
                "id": "913516",
                "profession": "演员",
                "roleName": "格莫拉 Gamora"
            }, {
                "artisteName": "凯伦·吉兰",
                "artisteNameEn": "Karen Gillan",
                "avatar": "i4/TB1xc_7etLO8KJjSZFxXXaGEVXa_.jpg",
                "bornDay": "1987-11-28",
                "id": "1426693",
                "profession": "演员",
                "roleName": "星云 Nebula"
            }, {
                "artisteName": "保罗·贝坦尼",
                "artisteNameEn": "Paul Bettany",
                "avatar": "i2/TB185yuJFXXXXXdXpXXXXXXXXXX_.jpg",
                "bornDay": "1971-05-27",
                "id": "915338",
                "profession": "演员",
                "roleName": "幻视 Vision"
            }, {
                "artisteName": "伊丽莎白·奥尔森",
                "artisteNameEn": "Elizabeth Olsen",
                "avatar": "i1/TB1_j47JFXXXXcsXVXXXXXXXXXX_.jpg",
                "bornDay": "1989-02-16",
                "id": "1806378",
                "profession": "演员",
                "roleName": "猩红女巫"
            }, {
                "artisteName": "汤姆·希德勒斯顿",
                "artisteNameEn": "Tom Hiddleston",
                "avatar": "i1/TB1_4N3JpXXXXbVXpXXXXXXXXXX_.jpg",
                "bornDay": "1981-02-09",
                "id": "1117773",
                "profession": "演员",
                "roleName": "洛基 Loki"
            }, {
                "artisteName": "戴夫·巴蒂斯塔",
                "artisteNameEn": "Dave Bautista",
                "avatar": "i4/TB1QNmCennI8KJjSszgXXc8ApXa_.jpg",
                "bornDay": "1969-01-18",
                "id": "917063",
                "profession": "演员",
                "roleName": "Drax"
            }, {
                "artisteName": "庞·克莱门捷夫",
                "artisteNameEn": "Pom Klementieff",
                "avatar": "i4/TB1lUJ0JpXXXXXxXFXXXXXXXXXX_.jpg",
                "bornDay": "1986-05-18",
                "id": "1494016",
                "profession": "演员",
                "roleName": " 螳螂女 Mantis"
            }],
            "description": "漫威影业为您倾力呈现万众期待的终极力作《复仇者联盟3：无限战争》！复仇者联盟的一众超级英雄，必须抱着牺牲一切的信念，与史上最强大反派灭霸(Thanos)殊死一搏，阻止其摧毁宇宙的邪恶计划。",
            "director": "苏伦",
            "duration": "151",
            "id": "156841",
            "openCountry": "中国大陆",
            "openDay": "2018-05-11 00:00:00",
            "openTime": "2018-05-11",
            "poster": "i4/TB1xcwSheySBuNjy1zdXXXPxFXa_.jpg",
            "showMark": "IMAX3D",
            "showName": "复仇者联盟3：无限战争",
            "showNameEn": "Avengers: Infinity War",
            "type": "动作,冒险,奇幻",
            "wantCount": "1016278",
            "remark": "8.8",
            "remarkCount": "2183891",
            "recommendStr": "81%",
            "country": "美国"
        }
    }
}
